wowool/analysis.py
wowool/analysis_parser.py
wowool/config.py
wowool/diagnostic.py
wowool/error.py
wowool/visitor.py
wowool/wow.py
wowool/annotation/__init__.py
wowool/annotation/annotation.py
wowool/annotation/concept.py
wowool/annotation/paragraph.py
wowool/annotation/sentence.py
wowool/annotation/token.py
wowool/apps/info.py
wowool/common/pipeline/__init__.py
wowool/common/pipeline/objects.py
wowool/document/__init__.py
wowool/document/document.py
wowool/document/factory.py
wowool/document/apps/chunks.py
wowool/document/apps/themes.py
wowool/document/apps/topics.py
wowool/io/console/__init__.py
wowool/io/console/argument_parser.py
wowool/io/console/console.py
wowool/io/provider/__init__.py
wowool/io/provider/docx.py
wowool/io/provider/factory.py
wowool/io/provider/file.py
wowool/io/provider/html.py
wowool/io/provider/html_v2.py
wowool/io/provider/input_provider.py
wowool/io/provider/pdf.py
wowool/io/provider/pdf_no_layout.py
wowool/io/provider/rtf.py
wowool/io/provider/str.py
wowool/portal/__init__.py
wowool/portal/client/__init__.py
wowool/portal/client/argument_parser.py
wowool/portal/client/cli.py
wowool/portal/client/component.py
wowool/portal/client/defines.py
wowool/portal/client/environment.py
wowool/portal/client/error.py
wowool/portal/client/httpcode.py
wowool/portal/client/pipeline.py
wowool/portal/client/portal.py
wowool/portal/client/service.py
wowool/portal/client/entity_graph/__init__.py
wowool/portal/client/entity_graph/__main__.py
wowool/portal/client/entity_graph/argument_parser.py
wowool/portal/client/entity_mapper/__main__.py
wowool/portal/client/entity_mapper/argument_parser.py
wowool/portal/client/wow/__main__.py
wowool/portal/client/wow/argument_parser.py
wowool/portal/client/wow/command/__init__.py
wowool/portal/client/wow/command/components.py
wowool/portal/client/wow/command/list.py
wowool/portal/client/wow/command/process.py
wowool/portal/client/wow/command/version.py
wowool/string/__init__.py
wowool/tool/woc/create.py
wowool_portal_client-0.1.0.dist-info/METADATA
wowool_portal_client-0.1.0.dist-info/WHEEL
wowool_portal_client-0.1.0.dist-info/entry_points.txt
wowool_portal_client-0.1.0.dist-info/top_level.txt
wowool_portal_client-0.1.0.dist-info/RECORD
