Metadata-Version: 2.1
Name: wowool-portal-client
Version: 0.1.0
Summary: The Wowool Portal Client
Home-page: https://www.wowool.com/
Author: Wowool
Author-email: info@wowool.com
Requires-Python: >=3.11
Requires-Dist: requests
